pcd_py/__init__.py
pcd_py/pcd_py.abi3.so
pcd_py-0.2.0.dist-info/METADATA
pcd_py-0.2.0.dist-info/WHEEL
pcd_py-0.2.0.dist-info/licenses/LICENSE
pcd_py-0.2.0.dist-info/RECORD
