Metadata-Version: 2.4
Name: pcd-py
Version: 0.2.0
Classifier: Programming Language :: Rust
Classifier: Programming Language :: Python :: Implementation :: CPython
Classifier: Programming Language :: Python :: Implementation :: PyPy
Requires-Dist: numpy>=2.2.6
License-File: LICENSE
Summary: `pcd-py` is a high-speed Python library for reading and writing PCD (Point Cloud Data) files, powered by a core implementation in Rust (`rs-pcd`). It integrates seamlessly with **NumPy** for efficient data handling.
Author-email: bigpear0201 <bigpear0201@gmail.com>
Requires-Python: >=3.8
Project-URL: Homepage, https://github.com/bigpear0201/pcd-py
